markovianbandit/__init__.py
markovianbandit/markovianbandit.py
markovianbandit/whittle_computation.py
markovianbandit_pkg-0.4.dist-info/LICENSE
markovianbandit_pkg-0.4.dist-info/METADATA
markovianbandit_pkg-0.4.dist-info/WHEEL
markovianbandit_pkg-0.4.dist-info/top_level.txt
markovianbandit_pkg-0.4.dist-info/RECORD
