Metadata-Version: 2.1
Name: markovianbandit-pkg
Version: 0.4
Summary: Library to compute Gittins and Whittle index for Markovian Bandits
Home-page: https://gitlab.inria.fr/markovianbandit/markovianbandit
Author: Nicolas Gast
Author-email: nicolas.gast@inria.fr
Project-URL: Bug Tracker, https://gitlab.inria.fr/markovianbandit/markovianbandit/issues
Classifier: Programming Language :: Python :: 3
Classifier: License :: OSI Approved :: MIT License
Classifier: Operating System :: OS Independent
Requires-Python: >=3.6
License-File: LICENSE
